setup.cfg
setup.py
qcos_cli/__init__.py
qcos_cli/cli.py
qcos_cli/config.py
qcos_cli/dec.py
qcos_cli/go.py
qcos_cli.egg-info/PKG-INFO
qcos_cli.egg-info/SOURCES.txt
qcos_cli.egg-info/dependency_links.txt
qcos_cli.egg-info/entry_points.txt
qcos_cli.egg-info/requires.txt
qcos_cli.egg-info/top_level.txt