Metadata-Version: 1.1
Name: qcos-cli
Version: 0.2
Summary: qcos python sdk cli wrapper
Home-page: https://github.com/AnyISalIn/qcos_cli
Author: AnyISalIn
Author-email: anyisalin@gmail.com
License: UNKNOWN
Platform: UNKNOWN
Classifier: Programming Language :: Python :: 2.7
